{
  "id": "exthisdsver:./archive.zip",
  "type": "dldist:Distribution",
  "has_part": [
    {
      "id": "exthisdsver:./archive.zip/subdir",
      "attributes": [
        {
          "predicate": "dcterms:description",
          "type": "dlthings:AttributeSpecification",
          "value": "A subdirectory"
        }
      ],
      "type": "dldist:Distribution",
      "has_part": [
        {
          "id": "exthisdsver:./archive.zip/subdir/file.txt",
          "attributes": [
            {
              "predicate": "dcterms:description",
              "type": "dlthings:AttributeSpecification",
              "value": "A file"
            }
          ],
          "type": "dldist:Distribution"
        }
      ],
      "qualified_part": [
        {
          "name": "file.txt",
          "object": "exthisdsver:./archive.zip/subdir/file.txt"
        }
      ]
    }
  ],
  "qualified_part": [
    {
      "name": "subdir",
      "object": "exthisdsver:./archive.zip/subdir"
    }
  ],
  "@type": "Distribution"
}
